ezbootstrap/__init__.py
ezbootstrap/core.py
ezbootstrap-0.0.3.dist-info/METADATA
ezbootstrap-0.0.3.dist-info/WHEEL
ezbootstrap-0.0.3.dist-info/licence.txt
ezbootstrap-0.0.3.dist-info/top_level.txt
ezbootstrap-0.0.3.dist-info/RECORD
