Metadata-Version: 2.1
Name: ezbootstrap
Version: 0.0.3
Summary: Bootstrap statistics package.
Home-page: https://github.com/Ruairi-osul/ezbootstrap
Author: Ruairi O'Sullivan
Author-email: ruairi.osullivan.work@gmail.com
License: GNU GPLv3
Project-URL: Source, https://github.com/Ruairi-osul/ezbootstrap
Keywords: statistics scientific-computing data data-science bootstrap
Requires-Python: >=3.3
License-File: licence.txt
Requires-Dist: numpy
Requires-Dist: numba
